pymoodeng/__init__.py
pymoodeng/anomaly.py
pymoodeng/constants.py
pymoodeng/core.py
pymoodeng/manuvers.py
pymoodeng/objects.py
pymoodeng/orbital_conversions.py
pymoodeng/plotting.py
pymoodeng-1.0.1.dist-info/METADATA
pymoodeng-1.0.1.dist-info/WHEEL
pymoodeng-1.0.1.dist-info/top_level.txt
pymoodeng-1.0.1.dist-info/RECORD
