Metadata-Version: 2.4
Name: pymoodeng
Version: 1.0.1
Summary: A Python package for simple system simulations and potential transition fuel calculations.
Author: ['Kiss Márkus', 'Tari Zalán', 'Varga Benedek']
Author-email: Tari Zalán <tari.zalan@itk.ppke.hu>, Varga Benedek <varga.benedek@hallgato.ppke.hu>, Kiss Márkus <kiss.markus@hallgato.ppke.hu>
License-Expression: MIT
Project-URL: Homepage, https://github.com/tarza17/PyMOODENG
Project-URL: Issues, https://github.com/tarza17/PyMOODENG/issues
Classifier: Programming Language :: Python :: 3.12
Classifier: Operating System :: OS Independent
Requires-Python: >=3.9
Requires-Dist: numpy>=2.2.4
Requires-Dist: pandas>=2.2.3
Requires-Dist: matplotlib>=3.10.1
Requires-Dist: pyqt5>=5.15.11
Requires-Dist: sphinx>=8.2.3
Requires-Dist: sphinx_rtd_theme>=3.0.2
Provides-Extra: docs
Requires-Dist: sphinx; extra == "docs"
Requires-Dist: sphinx_rtd_theme; extra == "docs"
Dynamic: author
